{
    "last_update": "2026-03-29 08:36:19 UTC",
    "portfolio": [
        {
            "Asset": "INJ/USDT",
            "Side": "SHORT",
            "Weight": 0.1592,
            "Forecast": 22.18,
            "Profit Factor": 2.71,
            "Calmar": 1.08
        },
        {
            "Asset": "SOL/USDT",
            "Side": "SHORT",
            "Weight": 0.1343,
            "Forecast": 18.71,
            "Profit Factor": 2.89,
            "Calmar": 2.72
        },
        {
            "Asset": "AVAX/USDT",
            "Side": "SHORT",
            "Weight": 0.1319,
            "Forecast": 18.38,
            "Profit Factor": 2.68,
            "Calmar": 2.16
        },
        {
            "Asset": "DOT/USDT",
            "Side": "SHORT",
            "Weight": 0.1314,
            "Forecast": 18.3,
            "Profit Factor": 2.64,
            "Calmar": 2.04
        },
        {
            "Asset": "LINK/USDT",
            "Side": "SHORT",
            "Weight": 0.1233,
            "Forecast": 17.18,
            "Profit Factor": 2.6,
            "Calmar": 2.28
        },
        {
            "Asset": "TIA/USDT",
            "Side": "SHORT",
            "Weight": 0.1126,
            "Forecast": 15.68,
            "Profit Factor": 2.32,
            "Calmar": 1.64
        },
        {
            "Asset": "NEAR/USDT",
            "Side": "SHORT",
            "Weight": 0.1078,
            "Forecast": 15.02,
            "Profit Factor": 2.35,
            "Calmar": 2.08
        },
        {
            "Asset": "FET/USDT",
            "Side": "SHORT",
            "Weight": 0.0994,
            "Forecast": 13.85,
            "Profit Factor": 2.23,
            "Calmar": 2.0
        }
    ]
}